{
	"info": {
		"_postman_id": "1c54a10f-ec7e-4d0c-bad1-d1b770997afd",
		"name": "SOEN-E-Commerce",
		"schema": "https://schema.getpostman.com/json/collection/v2.1.0/collection.json",
		"_exporter_id": "8213730"
	},
	"item": [
		{
			"name": "localhost:3001/createUser",
			"request": {
				"method": "POST",
				"header": [],
				"body": {
					"mode": "raw",
					"raw": "{\r\n    \"email\": \"sarah@gmail.com\",\r\n    \"password\": \"password6\",\r\n    \"firstName\": \"Sarah\",\r\n    \"lastName\": \"Coney\",\r\n    \"phoneNumber\": \"+1 887 444 5515\"\r\n}",
					"options": {
						"raw": {
							"language": "json"
						}
					}
				},
				"url": {
					"raw": "localhost:3001/createUser",
					"host": [
						"localhost"
					],
					"port": "3001",
					"path": [
						"createUser"
					]
				}
			},
			"response": []
		},
		{
			"name": "localhost:3001/authenticateUser",
			"request": {
				"method": "POST",
				"header": [],
				"body": {
					"mode": "raw",
					"raw": "{\r\n    \"email\": \"san@gmail.com\",\r\n    \"password\": \"password\"\r\n}",
					"options": {
						"raw": {
							"language": "json"
						}
					}
				},
				"url": {
					"raw": "localhost:3001/authenticateUser",
					"host": [
						"localhost"
					],
					"port": "3001",
					"path": [
						"authenticateUser"
					]
				}
			},
			"response": []
		},
		{
			"name": "localhost:3001/addProductsToCatalog",
			"request": {
				"method": "POST",
				"header": [],
				"url": {
					"raw": "localhost:3001/addProductsToCatalog",
					"host": [
						"localhost"
					],
					"port": "3001",
					"path": [
						"addProductsToCatalog"
					]
				}
			},
			"response": []
		},
		{
			"name": "localhost:3001/getAllProducts",
			"request": {
				"method": "POST",
				"header": [],
				"url": {
					"raw": "localhost:3001/getAllProducts",
					"host": [
						"localhost"
					],
					"port": "3001",
					"path": [
						"getAllProducts"
					]
				}
			},
			"response": []
		},
		{
			"name": "localhost:3001/getProductDetails",
			"request": {
				"method": "POST",
				"header": [],
				"body": {
					"mode": "raw",
					"raw": "{\r\n   \"productId\": 2\r\n}",
					"options": {
						"raw": {
							"language": "json"
						}
					}
				},
				"url": {
					"raw": "localhost:3001/getProductDetails",
					"host": [
						"localhost"
					],
					"port": "3001",
					"path": [
						"getProductDetails"
					]
				}
			},
			"response": []
		},
		{
			"name": "localhost:3001/getAllProductCategories",
			"request": {
				"method": "GET",
				"header": [],
				"url": {
					"raw": "localhost:3001/getAllProductCategories",
					"host": [
						"localhost"
					],
					"port": "3001",
					"path": [
						"getAllProductCategories"
					]
				}
			},
			"response": []
		},
		{
			"name": "localhost:3001/getProductImage",
			"protocolProfileBehavior": {
				"disableBodyPruning": true
			},
			"request": {
				"method": "GET",
				"header": [],
				"body": {
					"mode": "raw",
					"raw": "",
					"options": {
						"raw": {
							"language": "json"
						}
					}
				},
				"url": {
					"raw": "localhost:3001/getProductImage/2.jpg",
					"host": [
						"localhost"
					],
					"port": "3001",
					"path": [
						"getProductImage",
						"2.jpg"
					]
				}
			},
			"response": []
		},
		{
			"name": "localhost:3001/",
			"request": {
				"method": "GET",
				"header": [],
				"url": {
					"raw": "localhost:3001/",
					"host": [
						"localhost"
					],
					"port": "3001",
					"path": [
						""
					]
				}
			},
			"response": []
		}
	]
}